pretix_bambora_payform/__init__.py
pretix_bambora_payform/bambora.py
pretix_bambora_payform/payment.py
pretix_bambora_payform/signals.py
pretix_bambora_payform/urls.py
pretix_bambora_payform/utils.py
pretix_bambora_payform/views.py
pretix_bambora_payform/locale/de/LC_MESSAGES/django.mo
pretix_bambora_payform/locale/de/LC_MESSAGES/django.po
pretix_bambora_payform/locale/de_Informal/.gitkeep
pretix_bambora_payform/locale/de_Informal/LC_MESSAGES/django.mo
pretix_bambora_payform/locale/de_Informal/LC_MESSAGES/django.po
pretix_bambora_payform/locale/de_informal/LC_MESSAGES/django.mo
pretix_bambora_payform/locale/de_informal/LC_MESSAGES/django.po
pretix_bambora_payform/locale/en/LC_MESSAGES/django.mo
pretix_bambora_payform/locale/en/LC_MESSAGES/django.po
pretix_bambora_payform/locale/fi/LC_MESSAGES/django.mo
pretix_bambora_payform/locale/fi/LC_MESSAGES/django.po
pretix_bambora_payform/static/pretix_bambora_payform/.gitkeep
pretix_bambora_payform/static/pretix_bambora_payform/payment_methods_banner.png
pretix_bambora_payform/static/pretix_bambora_payform/payment_methods/aktia.png
pretix_bambora_payform/static/pretix_bambora_payform/payment_methods/alandsbanken.png
pretix_bambora_payform/static/pretix_bambora_payform/payment_methods/americanexpress.png
pretix_bambora_payform/static/pretix_bambora_payform/payment_methods/danskebank.png
pretix_bambora_payform/static/pretix_bambora_payform/payment_methods/handelsbanken.png
pretix_bambora_payform/static/pretix_bambora_payform/payment_methods/mastercard.png
pretix_bambora_payform/static/pretix_bambora_payform/payment_methods/masterpass.png
pretix_bambora_payform/static/pretix_bambora_payform/payment_methods/mobilepay.png
pretix_bambora_payform/static/pretix_bambora_payform/payment_methods/nordea.png
pretix_bambora_payform/static/pretix_bambora_payform/payment_methods/osuuspankki.png
pretix_bambora_payform/static/pretix_bambora_payform/payment_methods/pivo.png
pretix_visma_pay-0.4.1.dist-info/LICENSE
pretix_visma_pay-0.4.1.dist-info/METADATA
pretix_visma_pay-0.4.1.dist-info/WHEEL
pretix_visma_pay-0.4.1.dist-info/entry_points.txt
pretix_visma_pay-0.4.1.dist-info/top_level.txt
pretix_visma_pay-0.4.1.dist-info/RECORD
