Metadata-Version: 2.1
Name: pretix-visma-pay
Version: 0.4.1
Summary: Payment plugin for Visma Pay
Home-page: https://gitlab.com/naaspeksi/pretix-visma-pay
Author: Jaakko Rinta-Filppula
Author-email: jaakko@r-f.fi
License: Apache
Platform: UNKNOWN
Requires-Dist: requests (>=2.24.0)
